seapie/__init__.py
seapie/commands.py
seapie/constants.py
seapie/helpers.py
seapie/repl.py
seapie-4.0.1.dist-info/METADATA
seapie-4.0.1.dist-info/WHEEL
seapie-4.0.1.dist-info/top_level.txt
seapie-4.0.1.dist-info/RECORD
