Metadata-Version: 2.4
Name: seapie
Version: 4.0.1
Summary: A Python debugger that drops you into a live >>> prompt at breakpoints
Author: Markus Hirsimäki
License: The Unlicense
Project-URL: homepage, https://github.com/hirsimaki-markus/seapie
Project-URL: issues, https://github.com/hirsimaki-markus/seapie/issues
Project-URL: license, https://choosealicense.com/licenses/unlicense/
Keywords: debugger,debug,debugging,breakpoint,pdb,repl,interactive,trace,stepping,seapie
Classifier: Development Status :: 5 - Production/Stable
Classifier: Programming Language :: Python
Classifier: License :: OSI Approved :: The Unlicense (Unlicense)
Classifier: Operating System :: OS Independent
